<?xml version="1.0" encoding="UTF-8" standalone="yes"?><data><vec_employees><id>118430731</id><work_place>1111</work_place><total_salary>606.0</total_salary><_base_salary>600.0</_base_salary><_id>118430731</_id><_name>Jorge Duran</_name><_phone>63040703</_phone><_work_place><code>1111</code><x>128</x><y>161</y><_code>1111</_code><_reference>San Jose</_reference><_zonage_percentage>15.0</_zonage_percentage></_work_place></vec_employees><vec_branch_offices><code>2222</code><x>154</x><y>106</y><_code>2222</_code><_reference>Heredia</_reference><_zonage_percentage>4.0</_zonage_percentage></vec_branch_offices><vec_branch_offices><code>1111</code><x>128</x><y>161</y><_code>1111</_code><_reference>San Jose</_reference><_zonage_percentage>15.0</_zonage_percentage></vec_branch_offices></data>